README.md
setup.cfg
setup.py
Password_Learner.egg-info/PKG-INFO
Password_Learner.egg-info/SOURCES.txt
Password_Learner.egg-info/dependency_links.txt
Password_Learner.egg-info/requires.txt
Password_Learner.egg-info/top_level.txt
pwdgen/__init__.py
pwdgen/password.py
pwdgen/password_generator.py
pwdlearn/__init__.py
pwdlearn/__main__.py